tabuparse/__init__.py
tabuparse/cli.py
tabuparse/config_parser.py
tabuparse/core.py
tabuparse/data_processor.py
tabuparse/output_writer.py
tabuparse/pdf_extractor.py
tabuparse-0.1.0.dist-info/METADATA
tabuparse-0.1.0.dist-info/WHEEL
tabuparse-0.1.0.dist-info/entry_points.txt
tabuparse-0.1.0.dist-info/licenses/LICENSE
tabuparse-0.1.0.dist-info/RECORD
