Metadata-Version: 2.4
Name: tabuparse
Version: 0.1.0
Summary: A Python CLI tool for extracting, normalizing, and merging tabular data from PDF documents
Project-URL: Homepage, https://github.com/lupeke/tabuparse
Project-URL: Repository, https://github.com/lupeke/tabuparse
Project-URL: Issues, https://github.com/lupeke/tabuparse/issues
Author-email: Daniel Dias <daniel@lupeke.dev>
License: MIT
License-File: LICENSE
Keywords: cli,data engineering,extraction,parsing,pdf,table,utility
Classifier: Development Status :: 3 - Alpha
Classifier: Intended Audience :: Developers
Classifier: License :: OSI Approved :: MIT License
Classifier: Programming Language :: Python :: 3
Classifier: Programming Language :: Python :: 3.11
Classifier: Programming Language :: Python :: 3.12
Classifier: Topic :: Office/Business
Classifier: Topic :: Text Processing
Classifier: Topic :: Utilities
Requires-Python: >=3.11
Requires-Dist: camelot-py>=0.10.1
Requires-Dist: click>=8.0.0
Requires-Dist: ghostscript>=0.8.0
Requires-Dist: pandas>=2.0.0
Requires-Dist: tomli>=2.0.0; python_version < '3.11'
Provides-Extra: dev
Requires-Dist: black>=23.0.0; extra == 'dev'
Requires-Dist: coverage>=7.0.0; extra == 'dev'
Requires-Dist: flake8>=6.0.0; extra == 'dev'
Requires-Dist: isort>=5.12.0; extra == 'dev'
Requires-Dist: mypy>=1.0.0; extra == 'dev'
Requires-Dist: pytest-asyncio>=0.21.0; extra == 'dev'
Requires-Dist: pytest>=7.0.0; extra == 'dev'
